README.md
setup.py
hjlibrary/__init__.py
hjlibrary/dictionary_process_module.py
hjlibrary/dictionary_sort_module.py
hjlibrary/list_process_module.py
hjlibrary/list_sort_module.py
hjlibrary/string_process_module.py
hjlibrary/string_reverse_module.py
hjlibrary/string_slicing_module.py
hjlibrary/string_sort_module.py
hjlibrary.egg-info/PKG-INFO
hjlibrary.egg-info/SOURCES.txt
hjlibrary.egg-info/dependency_links.txt
hjlibrary.egg-info/top_level.txt