Metadata-Version: 2.1
Name: hjlibrary
Version: 1.0
Summary: HJ first Python library
Author: Henry Jia
